{
  "Employee": [
    {
      "firstName": "aa",
      "middleName": "ssbb",
      "lastName": "bb",
      "moblie": 546544,
      "email": "sagar@gmail.com",
      "address": "716,Shastri Nagar Solapur",
      "street": "Plot NO.16 Shastri Nagar Solapur",
      "pincode": "413003",
      "city": "Solapur",
      "state": "Maharashtra",
      "country": "India",
      "id": 1
    },
    {
      "firstName": "sagar",
      "middleName": "vyankatesh",
      "lastName": "dussa",
      "moblie": 145644484,
      "email": "sagr@gmail.com",
      "address": "716,Shastri Nagar Solapur",
      "street": "Plot NO.16 Shastri Nagar Solapur",
      "pincode": "413003",
      "city": "Solapur",
      "state": "Maharashtra",
      "country": "India",
      "id": 2
    }
  ]
}